setup.py
sidrah/Binomialdistribution.py
sidrah/Gaussiandistribution.py
sidrah/Generaldistribution.py
sidrah/__init__.py
sidrah.egg-info/PKG-INFO
sidrah.egg-info/SOURCES.txt
sidrah.egg-info/dependency_links.txt
sidrah.egg-info/not-zip-safe
sidrah.egg-info/top_level.txt